qmatchatea/__init__.py
qmatchatea/interface.py
qmatchatea/par_simulations.py
qmatchatea/preprocessing.py
qmatchatea/py_emulator.py
qmatchatea/tensor_compiler.py
qmatchatea/version.py
qmatchatea/circuit/__init__.py
qmatchatea/circuit/circuit.py
qmatchatea/circuit/observables.py
qmatchatea/circuit/operations.py
qmatchatea/utils/__init__.py
qmatchatea/utils/backend.py
qmatchatea/utils/mpi_utils.py
qmatchatea/utils/qk_utils.py
qmatchatea/utils/simulation_results.py
qmatchatea/utils/tn_utils.py
qmatchatea/utils/utils.py
qmatchatea-1.5.6.dist-info/licenses/LICENSE
qmatchatea-1.5.6.dist-info/licenses/NOTICE
qmatchatea-1.5.6.dist-info/METADATA
qmatchatea-1.5.6.dist-info/WHEEL
qmatchatea-1.5.6.dist-info/top_level.txt
qmatchatea-1.5.6.dist-info/RECORD
