Metadata-Version: 2.4
Name: qmatchatea
Version: 1.5.6
Summary: Quantum matcha TEA python library for tensor network emulation of quantum circuits.
Home-page: https://baltig.infn.it/quantum_matcha_tea/py_api_quantum_matcha_tea
Author: Marco Ballarin, Francesco Pio Barone, Alberto Coppi, Daniel Jaschke, Guillermo Muñoz Menés, Davide Rattacaso, Nora Reinić
Author-email: quantumtea@lists.infn.it
Classifier: Programming Language :: Python :: 3
Classifier: Operating System :: OS Independent
Requires-Python: >=3.11
License-File: LICENSE
License-File: NOTICE
Requires-Dist: numpy>=1.26.0
Requires-Dist: scipy>=1.4.1
Requires-Dist: matplotlib>=3.1.3
Requires-Dist: qtealeaves<1.8.0,>=1.7.21
Requires-Dist: qredtea<0.4.0,>=0.3.13
Requires-Dist: qiskit<2.0.0,>=1.0.0
Requires-Dist: joblib
Requires-Dist: psutil
Dynamic: author
Dynamic: author-email
Dynamic: classifier
Dynamic: description
Dynamic: description-content-type
Dynamic: home-page
Dynamic: license-file
Dynamic: requires-dist
Dynamic: requires-python
Dynamic: summary
